<annotation>
	<folder>0817</folder>
	<filename>4f8a409e1184421aaab8e7d8518ac554.jpg</filename>
	<path>C:\Users\pui_s\Downloads\nabirds.tar\nabirds\images\0817\4f8a409e1184421aaab8e7d8518ac554.jpg</path>
	<source>
		<database>Unknown</database>
	</source>
	<size>
		<width>1024</width>
		<height>750</height>
		<depth>3</depth>
	</size>
	<segmented>0</segmented>
	<object>
		<name>bird</name>
		<pose>Unspecified</pose>
		<truncated>0</truncated>
		<difficult>0</difficult>
		<bndbox>
			<xmin>438</xmin>
			<ymin>96</ymin>
			<xmax>761</xmax>
			<ymax>728</ymax>
		</bndbox>
	</object>
</annotation>
